{
    "speed": 0.0,
    "moves": 26,
    "starLimits": {
        "one": 150,
        "two": 2000,
        "three": 5000
    },
    "floatingBlocksSet": "Standard",
    "musicTrack": 2,
    "background": "sky7.jpg",
    "lightIntensity": "Sunset",
    "pieces": [
        "LongI",
        "I",
        "ShortI",
        "B",
        "D",
        "Seven",
        "MirroredSeven",
        "Bomb",
        "RowBomb"
    ],
    "clearGrid": [
        "       ",
        "       ",
        "       ",
        "       ",
        "       ",
        "       ",
        "       ",
        "       ",
        "       ",
        "       ",
        "       ",
        "       ",
        "       ",
        " G G GL",
        "G G   L",
        " G G GL",
        "G   G L",
        " G G GL",
        "  G G L",
        "LG G  G",
        "L G G  ",
        "LG G G "
    ]
}
