{
    "speed": 0.0,
    "moves": 33,
    "twoStars": 28,
    "threeStars": 24,
    "background": "sky6.jpg",
    "lightIntensity": "Sunset",
    "pieces": [
        "LongI",
        "ShortI",
        "BigL",
        "B",
        "D",
        "Z",
        "MirroredZ",
        "Bomb",
        "RowBomb"
    ],
    "clearGrid": [
        "       ",
        "       ",
        "       ",
        "       ",
        "       ",
        "       ",
        "       ",
        "       ",
        "       ",
        "       ",
        "       ",
        "       ",
        "       ",
        " GG    ",
        "GGGG   ",
        "GGGG   ",
        "    GG ",
        "   GGGG",
        "   GGGG",
        " GG    ",
        "GGGG   ",
        "GGGG   ",
        "  GGGG ",
        " GGGGGG",
        " GGGGGG",
        "G     G",
        "GG   GG",
        "GG   GG",
        " GGGG  ",
        "GGGGGG ",
        "GGGGGG ",
        "G     G",
        "GG   GG",
        "GG   GG"
    ]
}
