{
    "speed": 0.0,
    "moves": 25,
    "twoStars": 22,
    "threeStars": 17,
    "floatingBlocksSet": "Standard",
    "background": "sky5.jpg",
    "lightIntensity": "Sunset",
    "pieces": [
        "LongI",
        "I",
        "L",
        "B",
        "D",
        "F",
        "MirroredF",
        "BigL",
        "RowBomb"
    ],
    "clearGrid": [
        "       ",
        "       ",
        "       ",
        "       ",
        "       ",
        "       ",
        "       ",
        "       ",
        "       ",
        "       ",
        "       ",
        "       ",
        "       ",
        "      G",
        "      G",
        "   GGGG",
        "   GGGG",
        "   GGGG",
        "GGGGGG ",
        "G      ",
        "G      ",
        "GGGG   ",
        "GGGG   ",
        "GGGG   ",
        " GGGGGG",
        "      G",
        "      G",
        "   GGGG",
        "   GGGG",
        "   GGGG"
    ]
}
