{
    "speed": 0.0,
    "moves": 35,
    "twoStars": 30,
    "threeStars": 25,
    "background": "sky6.jpg",
    "dark": true,
    "pieces": [
        "BigTriangle",
        "Diamond",
        "Pyramid",
        "Bomb",
        "RowBomb"
    ],
    "clearGrid": [
        "        ",
        "        ",
        "        ",
        "        ",
        "        ",
        "        ",
        "        ",
        "        ",
        "        ",
        "        ",
        "        ",
        "        ",
        "        ",
        "        ",
        "GGb    d",
        "GGGb  dG",
        "GGGGbdGG",
        "   GGGGG",
        "   GGGGG",
        "   GGGGG",
        "GGGGG   ",
        "GGGGG   ",
        "GGGGG   ",
        "     GGG",
        "b    GGG",
        "Gb   GGG"
    ]
}
