{
    "speed": 0.0,
    "moves": 35,
    "twoStars": 25,
    "threeStars": 15,
    "background": "sky3.jpg",
    "dark": false,
    "partOfTutorial": true,
    "pieces": [
        "LongI",
        "I",
        "L",
        "B",
        "D",
        "Seven",
        "MirroredSeven"
    ],
    "pieceSequence": [
        "MirroredSeven"
    ],
    "clearGrid": [
        "       ",
        "       ",
        "       ",
        "       ",
        "       ",
        "       ",
        "       ",
        "       ",
        "       ",
        "       ",
        "    gll",
        "    gyy",
        "    grr",
        " GGGGGG",
        "       ",
        "GGG    ",
        "GGG    ",
        "GGG    ",
        "GGGG G ",
        "GGGG G ",
        "  GGGGG",
        "GGGGG  ",
        "GGGGG  ",
        "GGGGG  "
    ]
}
