{
    "speed": 0.0,
    "moves": 55,
    "starLimits": {
        "one": 100,
        "two": 600,
        "three": 1200
    },
    "floatingBlocksSet": "Standard",
    "musicTrack": 2,
    "background": "sky3.jpg",
    "lightIntensity": "Daylight",
    "partOfTutorial": true,
    "pieces": [
        "LongI",
        "I",
        "B",
        "D",
        "Seven",
        "MirroredSeven",
        "RowBomb"
    ],
    "pieceSequence": [
        "RowBomb",
        "D"
    ],
    "clearGrid": [
        "       ",
        "       ",
        "       ",
        "       ",
        "       ",
        "       ",
        "       ",
        "       ",
        "       ",
        "       ",
        "      g",
        "     yr",
        "    lyr",
        "G   GGG",
        "GGG    ",
        "GGG    ",
        "GGG    ",
        "   GGGG",
        "   GGGG",
        "   GGGG",
        "   GGGG",
        "   GGGG",
        "   GGGG",
        "   GGGG",
        "   GGGG",
        "   GGGG",
        " GGGGGG",
        "GGG    ",
        "GGG    ",
        "GGG    ",
        "GGG    "
    ]
}
